kataria/__init__.py
kataria/common.py
kataria/iterable.py
kataria/option.py
kataria/result.py
kataria-0.1.0.dist-info/LICENSE
kataria-0.1.0.dist-info/METADATA
kataria-0.1.0.dist-info/WHEEL
kataria-0.1.0.dist-info/RECORD
