Metadata-Version: 2.1
Name: kataria
Version: 0.1.0
Summary: bringing rust's functional style to python
Home-page: https://github.com/0x18050e1501/kataria
License: MIT
Author: xenua
Author-email: git@xenua.me
Requires-Python: >=3.10,<4.0
Classifier: Intended Audience :: Developers
Classifier: License :: OSI Approved :: MIT License
Classifier: Programming Language :: Python :: 3
Classifier: Programming Language :: Python :: 3.10
Classifier: Programming Language :: Python :: 3.11
Classifier: Programming Language :: Rust
Project-URL: Repository, https://github.com/0x18050e1501/kataria
